KorAPClient/__init__.py
KorAPClient/__main__.py
KorAPClient/tests/__init__.py
KorAPClient/tests/test_korapclient.py
examples/collocates.py
examples/fetchAll.py
examples/github-example.py
examples/hello_world.py
examples/hello_world_interactive.py
examples/ids_theme.py
examples/jason.py
examples/make_sense.py
examples/pandas-bokeh.py
examples/stardust.py
examples/test.py
examples/variant_by_country_interactive_barchart.py
examples/writtenVSspoken.py
korapclient-1.2.1.dist-info/licenses/LICENSE.txt
src/pythonkorapclient/__init__.py
tests/__init__.py
korapclient-1.2.1.dist-info/METADATA
korapclient-1.2.1.dist-info/WHEEL
korapclient-1.2.1.dist-info/top_level.txt
korapclient-1.2.1.dist-info/RECORD
