Metadata-Version: 2.4
Name: KorAPClient
Version: 1.2.1
Summary: Client package to access KorAP's web service API
Author-email: Marc Kupietz <kupietz@ids-mannheim.de>, Tim Feldmüller <feldmueller@ids-mannheim.de>
License: BSD
Project-URL: Homepage, https://github.com/KorAP/PythonKorAPClient
Project-URL: Issues, https://github.com/KorAP/PythonKorAPClient/issues
Classifier: Intended Audience :: Developers
Classifier: Intended Audience :: Science/Research
Classifier: License :: OSI Approved :: BSD License
Classifier: Operating System :: OS Independent
Classifier: Programming Language :: Python :: 3
Classifier: Programming Language :: Python :: 3.10
Classifier: Programming Language :: Python :: 3.11
Classifier: Programming Language :: Python :: 3.12
Classifier: Programming Language :: Python :: 3.13
Classifier: Programming Language :: Python :: 3.8
Classifier: Programming Language :: Python :: 3.9
Requires-Python: >=3.7
License-File: LICENSE.txt
Requires-Dist: markdown
Requires-Dist: packaging
Requires-Dist: Pyarrow
Requires-Dist: pandas>=1.2
Requires-Dist: rpy2>=3.3
Dynamic: license-file
